cmq/__init__.py
cmq/account.py
cmq/cmq_client.py
cmq/cmq_exception.py
cmq/cmq_http.py
cmq/cmq_tool.py
cmq/queue.py
cmq/sign.py
cmq/subscription.py
cmq/topic.py
qcloud_cmq_sdk-0.1.dist-info/DESCRIPTION.rst
qcloud_cmq_sdk-0.1.dist-info/METADATA
qcloud_cmq_sdk-0.1.dist-info/RECORD
qcloud_cmq_sdk-0.1.dist-info/WHEEL
qcloud_cmq_sdk-0.1.dist-info/metadata.json
qcloud_cmq_sdk-0.1.dist-info/top_level.txt
