Metadata-Version: 2.0
Name: qcloud-cmq-sdk
Version: 0.1
Summary: Tencent Cloud SDK for CMQ API 2.0
Home-page: https://github.com/tencentyun/cmq-python-sdk
Author: Tencent Cloud CMQ Team
Author-email: yorkxyzhang@tencent.com
License: Apache License 2.0
Platform: any
Classifier: Development Status :: 5 - Production/Stable
Classifier: Intended Audience :: Developers
Classifier: License :: OSI Approved :: Apache Software License
Classifier: Programming Language :: Python
Classifier: Programming Language :: Python :: 2.7
